setup.py
src/dt_state_estimation/__init__.py
src/dt_state_estimation/lane_filter/__init__.py
src/dt_state_estimation/lane_filter/lane_filter.py
src/dt_state_estimation/lane_filter/rendering.py
src/dt_state_estimation/lane_filter/types.py
src/dt_state_estimation/lane_filter/assets/lane_filter_grid.png
src/dt_state_estimation/wheel_odometry/__init__.py
src/dt_state_estimation/wheel_odometry/types.py
src/dt_state_estimation/wheel_odometry/utils.py
src/dt_state_estimation/wheel_odometry/wheel_odometer.py
src/lib_dt_state_estimation.egg-info/PKG-INFO
src/lib_dt_state_estimation.egg-info/SOURCES.txt
src/lib_dt_state_estimation.egg-info/dependency_links.txt
src/lib_dt_state_estimation.egg-info/requires.txt
src/lib_dt_state_estimation.egg-info/top_level.txt