Metadata-Version: 2.1
Name: lib-dt-state-estimation
Version: 0.0.10
Home-page: http://github.com/duckietown/lib-dt-state-estimation
Author: Andrea F. Daniele
Author-email: afdaniele@duckietown.com
